nf_presentation/__init__.py
nf_presentation/data_classes.py
nf_presentation/from-training.py
nf_presentation/html_renderer.py
nf_presentation/logger.py
nf_presentation/scheme_renderer.py
nf_presentation/settings.py
nf_presentation/_settings/__init__.py
nf_presentation/_settings/basic.py
nf_presentation/_settings/compact_layout.py
nf_presentation/_settings/data.py
nf_presentation/assets/__init__.py
nf_presentation/assets/animation_google_icon.png
nf_presentation/assets/animation_google_icon.svg
nf_presentation/assets/event_data.json
nf_presentation/assets/exercise_test_data.json
nf_presentation/assets/exercise_test_data_new.json
nf_presentation/assets/fallback_scheme.png
nf_presentation/assets/movie_google_icon.png
nf_presentation/assets/movie_google_icon.svg
nf_presentation/assets/rfs_logo.png
nf_presentation/assets/training_data.json
nf_presentation/assets/training_data_2.json
nf_presentation/builders/__init__.py
nf_presentation/builders/base.py
nf_presentation/builders/image_builder.py
nf_presentation/builders/paragraph_builder.py
nf_presentation/builders/presentation_builder.py
nf_presentation/builders/slide_builder.py
nf_presentation/builders/table_builder.py
nf_presentation/builders/text_builder.py
nf_presentation/renderers/__init__.py
nf_presentation/renderers/base_renderer.py
nf_presentation/renderers/compact_renderer.py
nf_presentation-0.3.2.dist-info/METADATA
nf_presentation-0.3.2.dist-info/WHEEL
nf_presentation-0.3.2.dist-info/dependency_links.txt
nf_presentation-0.3.2.dist-info/top_level.txt
nf_presentation-0.3.2.dist-info/RECORD
