Metadata-Version: 2.1
Name: nf-presentation
Version: 0.3.2
Summary: UNKNOWN
Home-page: https://github.com/thefrol/nanofootball-presentation-maker
Author: Dmitriy Frolenko
Author-email: orangefrol@gmail.com
License: MIT
Platform: UNKNOWN
Requires-Python: >3.7.0
Requires-Dist: python-pptx
Requires-Dist: CairoSVG
Requires-Dist: html2text
Requires-Dist: typing-extensions
